api/v1/__init__.py
api/v1/etcd.py
api/v1/mongo.py
core/__init__.py
core/config.py
core/consts.py
core/events.py
cron_api/__init__.py
cron_api/main.py
models/__init__.py
models/log.py
services/__init__.py
services/etcd.py
services/mongodb.py
utils/__init__.py
cron_api-0.1.3.dist-info/METADATA
cron_api-0.1.3.dist-info/WHEEL
cron_api-0.1.3.dist-info/entry_points.txt
cron_api-0.1.3.dist-info/RECORD
