Metadata-Version: 2.4
Name: cron-api
Version: 0.1.3
Summary: 定时任务api
Requires-Python: >=3.10
Requires-Dist: etcd3>=0.12.0
Requires-Dist: fastapi>=0.115.5
Requires-Dist: motor>=3.6.0
Requires-Dist: protobuf<=3.20.0
Requires-Dist: pydantic-settings>=2.6.1
Requires-Dist: pydantic>=2.9.2
Requires-Dist: typer>=0.13.1
Requires-Dist: uvicorn>=0.32.0
